{
  "main": {
    "id": "dc533feff9741f0e",
    "type": "split",
    "children": [
      {
        "id": "a4636fba3a0d41bc",
        "type": "tabs",
        "children": [
          {
            "id": "605222c4d2d586e1",
            "type": "leaf",
            "state": {
              "type": "markdown",
              "state": {
                "file": "Active Information Gathering.md",
                "mode": "source",
                "source": false
              },
              "icon": "lucide-file",
              "title": "Active Information Gathering"
            }
          },
          {
            "id": "44d8b2cbdd4fc1bd",
            "type": "leaf",
            "state": {
              "type": "markdown",
              "state": {
                "file": "Vulnerability Assessment.md",
                "mode": "source",
                "source": false
              },
              "icon": "lucide-file",
              "title": "Vulnerability Assessment"
            }
          },
          {
            "id": "a99dfa72918ad4e0",
            "type": "leaf",
            "state": {
              "type": "graph",
              "state": {},
              "icon": "lucide-git-fork",
              "title": "Graph view"
            }
          }
        ]
      }
    ],
    "direction": "vertical"
  },
  "left": {
    "id": "d1124f46aae38b75",
    "type": "split",
    "children": [
      {
        "id": "187323bfe548a4e4",
        "type": "tabs",
        "children": [
          {
            "id": "8f3ff7cbdf6f83de",
            "type": "leaf",
            "state": {
              "type": "file-explorer",
              "state": {
                "sortOrder": "byModifiedTimeReverse",
                "autoReveal": false
              },
              "icon": "lucide-folder-closed",
              "title": "Files"
            }
          },
          {
            "id": "68cc88ec50cf3df4",
            "type": "leaf",
            "state": {
              "type": "search",
              "state": {
                "query": "",
                "matchingCase": false,
                "explainSearch": false,
                "collapseAll": false,
                "extraContext": false,
                "sortOrder": "alphabetical"
              },
              "icon": "lucide-search",
              "title": "Search"
            }
          },
          {
            "id": "a8fcb3d5be63a9af",
            "type": "leaf",
            "state": {
              "type": "bookmarks",
              "state": {},
              "icon": "lucide-bookmark",
              "title": "Bookmarks"
            }
          }
        ]
      }
    ],
    "direction": "horizontal",
    "width": 200
  },
  "right": {
    "id": "c896f9710359d1ce",
    "type": "split",
    "children": [
      {
        "id": "a6165088685d5400",
        "type": "tabs",
        "children": [
          {
            "id": "ccf0dbb78d048066",
            "type": "leaf",
            "state": {
              "type": "backlink",
              "state": {
                "file": "System-Host based attacks.md",
                "collapseAll": false,
                "extraContext": false,
                "sortOrder": "alphabetical",
                "showSearch": false,
                "searchQuery": "",
                "backlinkCollapsed": false,
                "unlinkedCollapsed": true
              },
              "icon": "links-coming-in",
              "title": "Backlinks for System-Host based attacks"
            }
          },
          {
            "id": "115e724e35ca5f64",
            "type": "leaf",
            "state": {
              "type": "outgoing-link",
              "state": {
                "linksCollapsed": false,
                "unlinkedCollapsed": true
              },
              "icon": "links-going-out",
              "title": "Outgoing links"
            }
          },
          {
            "id": "aa2cbfeb6b0ecc56",
            "type": "leaf",
            "state": {
              "type": "tag",
              "state": {
                "sortOrder": "frequency",
                "useHierarchy": true,
                "showSearch": false,
                "searchQuery": ""
              },
              "icon": "lucide-tags",
              "title": "Tags"
            }
          },
          {
            "id": "fd9a3270e1063c15",
            "type": "leaf",
            "state": {
              "type": "outline",
              "state": {
                "followCursor": false,
                "showSearch": false,
                "searchQuery": ""
              },
              "icon": "lucide-list",
              "title": "Outline"
            }
          }
        ]
      }
    ],
    "direction": "horizontal",
    "width": 200,
    "collapsed": true
  },
  "left-ribbon": {
    "hiddenItems": {
      "switcher:Open quick switcher": false,
      "graph:Open graph view": false,
      "canvas:Create new canvas": false,
      "daily-notes:Open today's daily note": false,
      "templates:Insert template": false,
      "command-palette:Open command palette": false,
      "bases:Create new base": false
    }
  },
  "active": "605222c4d2d586e1",
  "lastOpenFiles": [
    "Assessment Methodologies.md",
    "Enumeration.md",
    "Networking and Enumeration.md",
    "Vulnerability Assessment.md",
    "Pasted image 20250918022533.png",
    "Active Information Gathering.md",
    "README.md",
    "Host & Network Auditing.md",
    "Passive Information Gathering.md",
    "Network-based attacks.md",
    "Pasted image 20250917231037.png",
    "Pasted image 20250917230904.png",
    "Pasted image 20250917203034.png",
    "Pasted image 20250917203022.png",
    "Screenshot_2025-09-17_13_45_15 1.png",
    "Screenshot_2025-09-17_13_45_15.png",
    "Windows Privilege Escalation.md",
    "System-Host based attacks.md",
    "Exploiting Windows Vulnerabilities.md",
    "The Metasploit Framework(MSF).md",
    "Host & Network Penetration Testing.md",
    "Linux Credentials Dumping.md",
    "Linux Privilege Escalation.md",
    "Exploiting Linux Vulnerabilities.md",
    "Windows Credential Dumping.md",
    "Pasted image 20250916121412.png",
    "Pasted image 20250916120855.png",
    "Screenshot_2025-09-15_10_56_25.png",
    "LM_working.md",
    "eJPT.md",
    "<h1> Windows Privilage Escalation </h1>.md",
    "<h1> Windows Privilage Escalation <",
    "Post-Exploitation.md",
    "Exploitation.md",
    "Social Engineering.md",
    "Web Application Penetration Testing.md"
  ]
}